<?xml version="1.0"?>
<nemsrusage>
  <walltime>
    <units>sec</units>
    <descr>total runtime of NEMS, excluding MPI setup time</descr>
    <stat type="max" by="rank">35.441804553</stat>
  </walltime>
  <systime>
    <units>percent</units>
    <descr>maximum system time used on any one rank</descr>
    <stat type="min" by="rank">1.182465359</stat>
    <stat type="max" by="rank">1.400686249</stat>
    <stat type="avg" by="rank">1.264656724</stat>
  </systime>
  <usertime>
    <units>percent</units>
    <descr>percent of time in user space any one rank</descr>
    <stat type="min" by="rank">98.599313751</stat>
    <stat type="max" by="rank">98.817534641</stat>
    <stat type="avg" by="rank">98.735343276</stat>
  </usertime>
  <memory>
    <units>MiB</units>
    <descr>maximum resident set size</descr>
    <values>
      <node name="c206-001.frontera.tacc.utexas.edu">
        <rank in_world="0">231.730468750</rank>
        <rank in_world="1">223.828125000</rank>
        <rank in_world="2">233.875000000</rank>
        <rank in_world="3">230.367187500</rank>
      </node>
    </values>
  </memory>
  <memory>
    <units>MiB</units>
    <descr>maximum resident set size</descr>
    <stat type="min" by="nodesum">919.800781250</stat>
    <stat type="max" by="nodesum">919.800781250</stat>
    <stat type="avg" by="nodesum">919.800781250</stat>
  </memory>
  <blocksread>
    <units>blocks</units>
    <descr>number of blocks read</descr>
    <stat type="min" by="nodesum">13264.000000000</stat>
    <stat type="max" by="nodesum">13264.000000000</stat>
    <stat type="avg" by="nodesum">13264.000000000</stat>
  </blocksread>
  <blockswritten>
    <units>blocks</units>
    <descr>number of blocks written</descr>
    <stat type="min" by="nodesum">177200.000000000</stat>
    <stat type="max" by="nodesum">177200.000000000</stat>
    <stat type="avg" by="nodesum">177200.000000000</stat>
  </blockswritten>
</nemsrusage>
